arduinoiot/__init__.py
iotrasp-2.0.dist-info/METADATA
iotrasp-2.0.dist-info/WHEEL
iotrasp-2.0.dist-info/top_level.txt
iotrasp-2.0.dist-info/RECORD
