Metadata-Version: 2.1
Name: iotrasp
Version: 2.0
Summary: package with iot codes
Author: Black_shark
